durkon/__init__.py
durkon/actual_modelling.py
durkon/calculus.py
durkon/export.py
durkon/geo.py
durkon/impose.py
durkon/metrics.py
durkon/misc.py
durkon/prep.py
durkon/radify.py
durkon/rele.py
durkon/util.py
durkon/viz.py
durkon/wraps.py
durkon-0.0.19.dist-info/METADATA
durkon-0.0.19.dist-info/WHEEL
durkon-0.0.19.dist-info/licenses/LICENSE
durkon-0.0.19.dist-info/RECORD
