Metadata-Version: 2.4
Name: durkon
Version: 0.0.19
Summary: A package for creating insurance-style GLM models, and extensions thereof.
Project-URL: Homepage, https://github.com/H-B-P/DURKON
Project-URL: Bug Tracker, https://github.com/H-B-P/DURKON/issues
Author-email: Hugh Panton <hugh.panton@protonmail.com>
License-File: LICENSE
Classifier: License :: OSI Approved :: The Unlicense (Unlicense)
Classifier: Operating System :: OS Independent
Classifier: Programming Language :: Python :: 3
Requires-Python: >=3.7
Requires-Dist: kaleido
Requires-Dist: numpy
Requires-Dist: pandas
Requires-Dist: plotly
Requires-Dist: scipy
